ynabtransactionadjuster/__init__.py
ynabtransactionadjuster/adjuster.py
ynabtransactionadjuster/client.py
ynabtransactionadjuster/exceptions.py
ynabtransactionadjuster/models/__init__.py
ynabtransactionadjuster/models/account.py
ynabtransactionadjuster/models/category.py
ynabtransactionadjuster/models/categorygroup.py
ynabtransactionadjuster/models/credentials.py
ynabtransactionadjuster/models/modifiedtransaction.py
ynabtransactionadjuster/models/modifier.py
ynabtransactionadjuster/models/modifiersubtransaction.py
ynabtransactionadjuster/models/payee.py
ynabtransactionadjuster/models/subtransaction.py
ynabtransactionadjuster/models/transaction.py
ynabtransactionadjuster/repos/__init__.py
ynabtransactionadjuster/repos/accountrepo.py
ynabtransactionadjuster/repos/categoryrepo.py
ynabtransactionadjuster/repos/payeerepo.py
ynabtransactionadjuster/serializer.py
ynabtransactionadjuster/signaturechecker.py
ynab_transaction_adjuster-2.0.2.dist-info/LICENSE
ynab_transaction_adjuster-2.0.2.dist-info/METADATA
ynab_transaction_adjuster-2.0.2.dist-info/WHEEL
ynab_transaction_adjuster-2.0.2.dist-info/RECORD
